discord/ext/ui/__init__.py
discord/ext/ui/helpers.py
discord/ext/ui/message.py
discord/ext/ui/paginator.py
discord/ext/ui/session.py
discord/ext/ui/version.py
dpy_ui-0.2.1.dist-info/LICENSE
dpy_ui-0.2.1.dist-info/METADATA
dpy_ui-0.2.1.dist-info/WHEEL
dpy_ui-0.2.1.dist-info/top_level.txt
dpy_ui-0.2.1.dist-info/RECORD
