Metadata-Version: 2.1
Name: dpy-ui
Version: 0.2.1
Summary: User interaction utilities for discord.py.
Home-page: https://github.com/Ikusaba-san/dpy-ui
Author: Ikusaba-san
License: MIT
Platform: UNKNOWN
Classifier: License :: OSI Approved :: MIT License
Classifier: Intended Audience :: Developers
Classifier: Natural Language :: English
Classifier: Operating System :: OS Independent
Classifier: Programming Language :: Python :: 3.6
Classifier: Programming Language :: Python :: 3.7
Classifier: Topic :: Internet
Classifier: Topic :: Software Development :: Libraries
Classifier: Topic :: Software Development :: Libraries :: Python Modules
Classifier: Topic :: Utilities
Requires-Python: >=3.6
Requires-Dist: dataclasses ; python_version < "3.7"
